pixivapibypasssni/__init__.py
pixivapibypasssni/client.py
pixivapibypasssni/common.py
pixivapibypasssni/enums.py
pixivapibypasssni/errors.py
pixivapibypasssni/models.py
pixiv_api_bypass_sni-1.0.1.dist-info/LICENSE
pixiv_api_bypass_sni-1.0.1.dist-info/METADATA
pixiv_api_bypass_sni-1.0.1.dist-info/WHEEL
pixiv_api_bypass_sni-1.0.1.dist-info/top_level.txt
pixiv_api_bypass_sni-1.0.1.dist-info/RECORD
