Metadata-Version: 2.1
Name: pixiv-api-bypass-sni
Version: 1.0.1
Summary: A fork of Pixiv API, which bypasses sni. Can be used without proxies.
Author: svjx18
Author-email: PleaseContactMe@Github.Issues
License: Apache-2.0
Project-URL: repository, https://github.com/svjx18/pixiv-api-bypass-sni
Requires-Python: ==3.*,>=3.6.0
License-File: LICENSE
Requires-Dist: cloudscraper ==1.*,>=1.2.48
Requires-Dist: requests ==2.*,>=2.0.0
Provides-Extra: dev
Requires-Dist: black ==20.*,>=20.8.0.b1 ; extra == 'dev'
Requires-Dist: dephell ==0.*,>=0.8.3 ; extra == 'dev'
Requires-Dist: flake8 ==3.*,>=3.7.0 ; extra == 'dev'
Requires-Dist: isort ==5.*,>=5.7.0 ; extra == 'dev'
Requires-Dist: pytest-cov ==2.*,>=2.11.1 ; extra == 'dev'
Requires-Dist: pytest ==6.*,>=6.2.2 ; extra == 'dev'
Requires-Dist: responses ==0.*,>=0.12.1 ; extra == 'dev'
Requires-Dist: snapshottest ==0.*,>=0.6.0 ; extra == 'dev'
Requires-Dist: sphinx-rtd-theme ==0.*,>=0.4.3 ; extra == 'dev'
Requires-Dist: sphinx ==2.*,>=2.1.0 ; extra == 'dev'
